varjson/__init__.py
varjson/envjson.py
varjson-0.1.0.dist-info/LICENSE
varjson-0.1.0.dist-info/METADATA
varjson-0.1.0.dist-info/WHEEL
varjson-0.1.0.dist-info/top_level.txt
varjson-0.1.0.dist-info/RECORD
