Metadata-Version: 2.1
Name: varjson
Version: 0.1.0
Summary: Simple JSON configuration file parser with easy access for structured data
Home-page: https://github.com/MLuehr/EnvJSON
Author: Mathias
License: MIT
Platform: any
Classifier: Operating System :: OS Independent
Classifier: License :: OSI Approved :: MIT License
Classifier: Topic :: Utilities
Classifier: Intended Audience :: Developers
Classifier: Topic :: Software Development :: Libraries :: Python Modules
Classifier: Programming Language :: Python :: 3.9
Classifier: Programming Language :: Python :: 3.10
Classifier: Programming Language :: Python :: 3.11
Classifier: Programming Language :: Python :: 3.12
Requires-Python: >=3.9
License-File: LICENSE
